[
  {
    "id": "#1001",
    "title": "Login Issue – User Unable to Access Account",
    "description": "Customer reports they are unable to log in even after resetting their password.",
    "status": "Open",
    "priority": "HIGH PRIORITY",
    "priorityColor": "text-red-600",
    "user": "John Doe",
    "date": "1/15/2024",
    "btnColor": "bg-[#E0F2FE]",
    "btnTextColor": "text-[#1E3A8A]"
  },
  {
    "id": "#1002",
    "title": "Payment Failure During Checkout",
    "description": "User attempted to complete purchase but payment was declined multiple times.",
    "status": "In Progress",
    "priority": "MEDIUM PRIORITY",
    "priorityColor": "text-yellow-600",
    "user": "Sarah Smith",
    "date": "1/16/2024",
    "btnColor": "bg-[#FEF9C3]",
    "btnTextColor": "text-[#854D0E]"
  },
  {
    "id": "#1003",
    "title": "Website Loading Very Slowly",
    "description": "Customer experiencing slow loading times on the dashboard page.",
    "status": "Open",
    "priority": "HIGH PRIORITY",
    "priorityColor": "text-red-600",
    "user": "Michael Brown",
    "date": "1/17/2024",
    "btnColor": "bg-[#FEE2E2]",
    "btnTextColor": "text-[#991B1B]"
  },
  {
    "id": "#1004",
    "title": "Error 404 on Profile Page",
    "description": "User receives a 404 error when trying to access their profile settings.",
    "status": "Resolved",
    "priority": "LOW PRIORITY",
    "priorityColor": "text-green-600",
    "user": "Emily Davis",
    "date": "1/18/2024",
    "btnColor": "bg-[#DCFCE7]",
    "btnTextColor": "text-[#166534]"
  },
  {
    "id": "#1005",
    "title": "Password Reset Email Not Received",
    "description": "Customer did not receive password reset email after multiple attempts.",
    "status": "Open",
    "priority": "MEDIUM PRIORITY",
    "priorityColor": "text-yellow-600",
    "user": "David Wilson",
    "date": "1/19/2024",
    "btnColor": "bg-[#FEF3C7]",
    "btnTextColor": "text-[#92400E]"
  },
  {
    "id": "#1006",
    "title": "Mobile App Crashing on Launch",
    "description": "App crashes immediately after opening on Android devices.",
    "status": "In Progress",
    "priority": "HIGH PRIORITY",
    "priorityColor": "text-red-600",
    "user": "Sophia Taylor",
    "date": "1/20/2024",
    "btnColor": "bg-[#FECACA]",
    "btnTextColor": "text-[#7F1D1D]"
  },
  {
    "id": "#1007",
    "title": "Unable to Upload Profile Picture",
    "description": "User receives an error when trying to upload a new profile photo.",
    "status": "Open",
    "priority": "LOW PRIORITY",
    "priorityColor": "text-green-600",
    "user": "James Anderson",
    "date": "1/21/2024",
    "btnColor": "bg-[#D1FAE5]",
    "btnTextColor": "text-[#065F46]"
  },
  {
    "id": "#1008",
    "title": "Incorrect Billing Amount Charged",
    "description": "Customer reports being charged more than the displayed price.",
    "status": "In Progress",
    "priority": "HIGH PRIORITY",
    "priorityColor": "text-red-600",
    "user": "Olivia Martinez",
    "date": "1/22/2024",
    "btnColor": "bg-[#FFE4E6]",
    "btnTextColor": "text-[#9F1239]"
  },
  {
    "id": "#1009",
    "title": "Notification Emails Not Sending",
    "description": "System is not sending email notifications to subscribed users.",
    "status": "Open",
    "priority": "MEDIUM PRIORITY",
    "priorityColor": "text-yellow-600",
    "user": "William Garcia",
    "date": "1/23/2024",
    "btnColor": "bg-[#FEF08A]",
    "btnTextColor": "text-[#713F12]"
  },
  {
    "id": "#1010",
    "title": "Search Function Not Returning Results",
    "description": "Users unable to find products using the search feature.",
    "status": "Resolved",
    "priority": "HIGH PRIORITY",
    "priorityColor": "text-red-600",
    "user": "Ava Rodriguez",
    "date": "1/24/2024",
    "btnColor": "bg-[#EDE9FE]",
    "btnTextColor": "text-[#5B21B6]"
  },
  {
    "id": "#1011",
    "title": "Two-Factor Authentication Code Invalid",
    "description": "Users report receiving invalid verification code during login.",
    "status": "Open",
    "priority": "HIGH PRIORITY",
    "priorityColor": "text-red-600",
    "user": "Daniel Hernandez",
    "date": "1/25/2024",
    "btnColor": "bg-[#FEE2E2]",
    "btnTextColor": "text-[#991B1B]"
  },
  {
    "id": "#1012",
    "title": "Dark Mode UI Alignment Issue",
    "description": "UI elements overlap when dark mode is enabled.",
    "status": "In Progress",
    "priority": "LOW PRIORITY",
    "priorityColor": "text-green-600",
    "user": "Mia Lopez",
    "date": "1/26/2024",
    "btnColor": "bg-[#E0E7FF]",
    "btnTextColor": "text-[#3730A3]"
  }
]